pymatrix.py
setup.py
pymatrix.egg-info/PKG-INFO
pymatrix.egg-info/SOURCES.txt
pymatrix.egg-info/dependency_links.txt
pymatrix.egg-info/entry_points.txt
pymatrix.egg-info/top_level.txt