Metadata-Version: 1.1
Name: pymatrix
Version: 3.0.0
Summary: A lightweight, easy-to-use matrix module in pure Python.
Home-page: https://github.com/dmulholland/pymatrix
Author: Darren Mulholland
Author-email: UNKNOWN
License: Public Domain
Platform: UNKNOWN
Classifier: Programming Language :: Python :: 3
Classifier: Operating System :: OS Independent
Classifier: License :: Public Domain
Classifier: Topic :: Scientific/Engineering :: Mathematics
